nodata/__init__.py
nodata/alphamask.py
nodata/blob.py
nodata/scripts/__init__.py
nodata/scripts/alpha.py
nodata/scripts/cli.py
nodata-0.5.0.dist-info/DESCRIPTION.rst
nodata-0.5.0.dist-info/METADATA
nodata-0.5.0.dist-info/RECORD
nodata-0.5.0.dist-info/WHEEL
nodata-0.5.0.dist-info/entry_points.txt
nodata-0.5.0.dist-info/metadata.json
nodata-0.5.0.dist-info/top_level.txt
