Metadata-Version: 2.0
Name: nodata
Version: 0.5.0
Summary: Utilities for handling nodata
Home-page: https://github.com/mapbox/nodata
Author: Damon Burgett
Author-email: damon@mapbox.com
License: MIT
Platform: UNKNOWN
Requires-Dist: click
Requires-Dist: raster-tester
Requires-Dist: rasterio (>=1.0a12)
Requires-Dist: rio-mucho
Requires-Dist: scikit-image
Requires-Dist: scipy
Provides-Extra: test
Requires-Dist: pytest; extra == 'test'
Requires-Dist: pytest-cov; extra == 'test'
